qgispluginci/__init__.py
qgispluginci/__main__.py
qgispluginci/changelog.py
qgispluginci/cli.py
qgispluginci/exceptions.py
qgispluginci/parameters.py
qgispluginci/plugins.xml.template
qgispluginci/release.py
qgispluginci/translation.py
qgispluginci/utils.py
qgispluginci/version_note.py
qgispluginci/translation_clients/__init__.py
qgispluginci/translation_clients/baseclient.py
qgispluginci/translation_clients/transifex.py
qgis_plugin_ci-2.8.10.dist-info/LICENSE
qgis_plugin_ci-2.8.10.dist-info/METADATA
qgis_plugin_ci-2.8.10.dist-info/WHEEL
qgis_plugin_ci-2.8.10.dist-info/entry_points.txt
qgis_plugin_ci-2.8.10.dist-info/top_level.txt
qgis_plugin_ci-2.8.10.dist-info/RECORD
