Metadata-Version: 2.1
Name: qgis-plugin-ci
Version: 2.8.10
Summary: Let qgis-plugin-ci package and release your QGIS plugins for you. Have a tea or go hiking meanwhile. Contains scripts to perform automated testing and deployment for QGIS plugins. These scripts are written for and tested on GitHub Actions, GitLab CI, Travis-CI, and Transifex.
Author-email: Denis Rouzaud <denis@opengis.ch>, Etienne Trimaille <etienne.trimaille@gmail.com>, Julien Moura <dev@ingeoveritas.com>
License: GPLv3
Project-URL: homepage, https://opengisch.github.io/qgis-plugin-ci/
Project-URL: documentation, https://opengisch.github.io/qgis-plugin-ci/
Project-URL: repository, https://github.com/opengisch/qgis-plugin-ci/
Project-URL: tracker, https://github.com/opengisch/qgis-plugin-ci/issues
Keywords: QGIS,CI,changelog,plugin
Classifier: Development Status :: 5 - Production/Stable
Classifier: Intended Audience :: System Administrators
Classifier: Intended Audience :: Developers
Classifier: Intended Audience :: Information Technology
Classifier: License :: OSI Approved :: GNU General Public License v3 or later (GPLv3+)
Classifier: Operating System :: OS Independent
Classifier: Programming Language :: Python :: 3
Classifier: Programming Language :: Python :: 3.8
Classifier: Programming Language :: Python :: 3.9
Classifier: Programming Language :: Python :: 3.10
Classifier: Programming Language :: Python :: 3.11
Classifier: Programming Language :: Python :: Implementation :: CPython
Classifier: Topic :: Scientific/Engineering :: GIS
Requires-Python: >=3.8
License-File: LICENSE
Requires-Dist: GitPython<3.2,>=3.1
Requires-Dist: PyGithub<2.6,>=1.54
Requires-Dist: PyQt5<5.16,>=5.15
Requires-Dist: pyqt5ac<1.3,>=1.2
Requires-Dist: python-slugify<8.1,>=4.0
Requires-Dist: pyyaml<6.1,>=5.4
Requires-Dist: six>=1.16.0
Requires-Dist: transifex-python<4.0,>=3.2
Requires-Dist: toml>=0.10.2
Provides-Extra: dev
Requires-Dist: black; extra == "dev"
Requires-Dist: flake8-builtins>=1.5; extra == "dev"
Requires-Dist: flake8-isort>=4.0; extra == "dev"
Requires-Dist: flake8-print>=5; extra == "dev"
Requires-Dist: pre-commit<4,>=3; extra == "dev"
Requires-Dist: nose2<0.16,>=0.15.1; extra == "dev"
